yyc/__init__.py
yyc/pipeline.py
yyc/scheme.py
yyc/utils/__init__.py
yyc/utils/data_handle.py
yyc/utils/index_operator.py
yyc/utils/log.py
yyc/utils/model_saver.py
yyc/utils/monitor.py
yyc/utils/rule_set.py
yyc/utils/validity.py
yyc-1.0.dist-info/METADATA
yyc-1.0.dist-info/WHEEL
yyc-1.0.dist-info/top_level.txt
yyc-1.0.dist-info/RECORD
